ap/topical/__init__.py
ap/topical/__version__.py
ap_topical-0.3.1.dist-info/METADATA
ap_topical-0.3.1.dist-info/WHEEL
ap_topical-0.3.1.dist-info/top_level.txt
ap_topical-0.3.1.dist-info/RECORD
