Metadata-Version: 2.1
Name: ap-topical
Version: 0.3.1
Summary: A simple, lightweight event pipeline in Python.
Home-page: https://github.com/annapoulakos/ap-topical
Author: Anna Poulakos
Author-email: anna.poulakos@gmail.com
Classifier: Development Status :: 4 - Beta
Classifier: Intended Audience :: Developers
Classifier: License :: OSI Approved :: MIT License
Classifier: Programming Language :: Python
Classifier: Programming Language :: Python :: 3
Classifier: Programming Language :: Python :: 3.9
